README.rst
setup.py
lastfmclient/__init__.py
lastfmclient/api.py
lastfmclient/async.py
lastfmclient/client.py
lastfmclient/exceptions.py
lastfmclient/package.py
lastfmclient.egg-info/PKG-INFO
lastfmclient.egg-info/SOURCES.txt
lastfmclient.egg-info/dependency_links.txt
lastfmclient.egg-info/requires.txt
lastfmclient.egg-info/top_level.txt