Metadata-Version: 1.1
Name: lastfmclient
Version: 0.0.3
Summary: Python client for the Last.fm API with a pythonic interface to all methods,
Home-page: https://github.com/jakubroztocil/lastfmclient
Author: UNKNOWN
Author-email: BSD
License: BSD
Download-URL: https://github.com/jakubroztocil/lastfmclient
Platform: UNKNOWN
